mrchef/__init__.py
mrchef/__main__.py
mrchef/cli.py
mrchef/lib.py
mrchef/nix/fetchMeal.nix
mrchef/nix/mkSingleMealDrvArgs.nix
mrchef/nix/mkWarmSrc.nix
mrchef/nix/mkPureWarmupHook/builder.py
mrchef/nix/mkPureWarmupHook/default.nix
mrchef/nix/modules/dream2nix/mrchef/default.nix
mrchef/nix/modules/dream2nix/mrchef/x86_64-linux.lock
mrchef-0.10.0.dist-info/LICENSE
mrchef-0.10.0.dist-info/METADATA
mrchef-0.10.0.dist-info/WHEEL
mrchef-0.10.0.dist-info/entry_points.txt
mrchef-0.10.0.dist-info/top_level.txt
mrchef-0.10.0.dist-info/RECORD
