Metadata-Version: 2.1
Name: mrchef
Version: 0.10.0
Summary: Metarepo Chef
Author-email: Moduon <info@moduon.team>, Jairo Llopis <jairo@moduon.team>
Maintainer-email: Moduon <info@moduon.team>
License: GNU GENERAL PUBLIC LICENSE
Project-URL: Homepage, https://gitlab.com/moduon/mrchef
Project-URL: Documentation, https://gitlab.com/moduon/mrchef/-/blob/main/README.md
Project-URL: Repository, https://gitlab.com/moduon/mrchef
Project-URL: Changelog, https://gitlab.com/moduon/mrchef/-/blob/main/CHANGELOG.md
Classifier: Development Status :: 4 - Beta
Classifier: Environment :: Console
Classifier: Intended Audience :: Developers
Classifier: Topic :: Software Development :: Build Tools
Classifier: Topic :: Software Development :: Version Control :: Git
Requires-Python: >=3.10
License-File: LICENSE
Requires-Dist: coloredlogs >=15.0.1
Requires-Dist: decorator >=5.1.1
Requires-Dist: git-autoshare >=1.0.0-beta.6
Requires-Dist: git-find-repos >=2.1.0
Requires-Dist: mergedeep >=1.3.4
Requires-Dist: plumbum >=1.7.2
Requires-Dist: requests >=2.27.1
Requires-Dist: rtoml >=0.9
Requires-Dist: tomlkit >=0.12.1
Requires-Dist: xdg >=5.1.1
Provides-Extra: dev
Requires-Dist: pytest >=7.2.1 ; extra == 'dev'
Requires-Dist: pytest-xdist >=3.2.1 ; extra == 'dev'
